{
  "document_type": "academic_paper",
  "title": "基于深度卷积结构的图像段落描述研究",
  "authors": [
    "未在原文中明确列出"
  ],
  "main_topic": "段落式图像描述任务，连接计算机视觉和自然语言处理两个关键领域",
  "research_problem": "当前段落式图像描述研究存在生成段落连贯性不足、图像信息损失和算法时间复杂度高等问题",
  "methodology": "提出了基于全卷积神经结构的段落式图像描述方法，包括全卷积解码器和融合区域注意力的段落式图像描述模型Dual-CNN",
  "key_innovations": [
    "全卷积解码器具有更大的长时记忆能力",
    "Dual-CNN模型融合区域提议网络和区域注意力模块",
    "提出衡量段落连贯性和句子多样度的指标"
  ],
  "experimental_results": "实验表明，所提方法在连贯性、详细度和多样度等方面优于基线方法，且具有更低的训练时间复杂度",
  "conclusions": "所提出的全卷积段落解码器和Dual-CNN模型在段落式图像描述任务上具有显著优势，提升了生成段落的质质量",
  "keywords": [
    "深度学习",
    "卷积神经网络",
    "段落式图像描述",
    "连贯性"
  ],
  "application_domains": [
    "未在原文中明确提到"
  ],
  "technical_concepts": [
    "全卷积神经结构",
    "层次性RNN解码器",
    "区域注意力机制",
    "Dual-CNN模型"
  ],
  "performance_metrics": "评测指标得分、连贯性指标得分、时间复杂度等",
  "summary": "本文针对当前段落式图像描述研究中存在的问题，提出了一种基于全卷积神经结构的新方法。通过实验验证，该方法在生成段落的连贯性、详细度和多样度方面取得了显著成效，为跨媒体智能领域的研究提供了重要进展。",
  "file_id": "基于深度卷积结构的图像段落描述研究_梁昊雨",
  "source_type": "cleaned",
  "text_length": 15854,
  "generation_time": "2025-07-31 21:38:43"
}